technical/__init__.py
technical/accdecoscillator.py
technical/aroon.py
technical/atr.py
technical/awesomeoscillator.py
technical/basicops.py
technical/bollinger.py
technical/cci.py
technical/crossover.py
technical/dema.py
technical/deviation.py
technical/directionalmove.py
technical/dma.py
technical/dpo.py
technical/dv2.py
technical/ema.py
technical/envelope.py
technical/hadelta.py
technical/heikinashi.py
technical/hma.py
technical/hurst.py
technical/ichimoku.py
technical/kama.py
technical/kst.py
technical/lrsi.py
technical/mabase.py
technical/macd.py
technical/momentum.py
technical/ols.py
technical/oscillator.py
technical/percentchange.py
technical/percentrank.py
technical/pivotpoint.py
technical/prettygoodoscillator.py
technical/priceoscillator.py
technical/psar.py
technical/rmi.py
technical/rsi.py
technical/sma.py
technical/smma.py
technical/stochastic.py
technical/trix.py
technical/tsi.py
technical/ultimateoscillator.py
technical/vortex.py
technical/williams.py
technical/wma.py
technical/zlema.py
technical/zlind.py
groxink_technical_indicators-0.1.3.dist-info/LICENSE.txt
groxink_technical_indicators-0.1.3.dist-info/METADATA
groxink_technical_indicators-0.1.3.dist-info/WHEEL
groxink_technical_indicators-0.1.3.dist-info/top_level.txt
groxink_technical_indicators-0.1.3.dist-info/RECORD
